chiplot_analyze/__init__.py
chiplot_analyze/chiplot.py
chiplot_analyze/chiplot_analyze.py
chiplot_analyze/dlog.py
chiplot_analyze/background_sub/__init__.py
chiplot_analyze/background_sub/bgsub.py
chiplot_analyze/background_sub/convhull.py
chiplot_analyze/background_sub/pchip.py
chiplot_analyze/background_sub/spline.py
chiplot_analyze/peak_analyzer/__init__.py
chiplot_analyze/peak_analyzer/centroid.py
chiplot_analyze/sample/Farman_0003.chi
chiplot_analyze/sample/Farman_0003.chil
chiplot_analyze/sample/Farman_0003.chir
chiplot_analyze/sample/Farman_0004.chi
chiplot_analyze/sample/__init__.py
chiplot_analyze/splitter/__init__.py
chiplot_analyze/splitter/splitter.py
chiplot_analyze-0.9.7.dist-info/DESCRIPTION.rst
chiplot_analyze-0.9.7.dist-info/METADATA
chiplot_analyze-0.9.7.dist-info/RECORD
chiplot_analyze-0.9.7.dist-info/WHEEL
chiplot_analyze-0.9.7.dist-info/entry_points.txt
chiplot_analyze-0.9.7.dist-info/metadata.json
chiplot_analyze-0.9.7.dist-info/top_level.txt
