Metadata-Version: 2.0
Name: chiplot-analyze
Version: 0.9.7
Summary: A general purpose GUI application used to analyze chiplots.
Home-page: https://github.com/biocatiit/Chiplot-analyze
Author: BioCAT
Author-email: biocat@lethocerus.biol.iit.edu
License: UNKNOWN
Keywords: chiplot analyze
Platform: UNKNOWN
Classifier: Development Status :: 3 - Alpha
Classifier: Programming Language :: Python :: 2
Classifier: Programming Language :: Python :: 2.7
Classifier: Programming Language :: Python :: 2 :: Only
Requires-Dist: matplotlib
